example/dig/counter.v
/*
* COUNTER.v -- Simple Digital Counter Example in Verilog
*
* (c) 2021 Harald Pretl (harald.pretl@jku.at)
* Johannes Kepler University Linz, Institute for Integrated Circuits
*/

module counter #(parameter WIDTH=4) (
  output reg [WIDTH-1:0] out_o,
  input                  clk_i,
  input	                 reset_i
);

  always @(posedge clk_i) begin
    // we use a synchronous reset
    if (reset_i) begin
      out_o <= {WIDTH{1'b0}};
    end else begin
      out_o <= out_o + 1'b1;
    end
  end

endmodule // counter

example/dig/counter_tb.v
/*
* COUNTER_tb.v -- Simple Digital Counter Example Testbench in Verilog
*
* (c) 2021 Harald Pretl (harald.pretl@jku.at)
* Johannes Kepler University Linz, Institute for Integrated Circuits
*/

`timescale 1ns / 1ns

`include "counter.v"

module counter_tb;

  // Make a reset that pulses once
  reg reset = 1'b0;
  initial begin
    #17 reset = 1'b1;
    #11 reset = 1'b0;
    #29 reset = 1'b1;
    #11 reset = 1'b0;
    #200 $finish; // this stops the simulation
  end

  // Make a regular pulsing clock
  reg clk = 1'b0;
  always #5 clk = ~clk;

  wire [3:0] value;
  
  // Instantiate the counter module and assign ports
  counter counter1 (
	  .out_o(value),
	  .clk_i(clk),
	  .reset_i(reset)
  );

  initial begin
     $dumpfile("counter_tb.vcd");
     $dumpvars(1, counter_tb);
     $monitor("At time %t, value = %h (%0d)", $time, value, value);
  end

endmodule // counter_tb

example/dig/counter_tb.vcd
$date
	Mon Dec 27 09:19:22 2021
$end
$version
	Icarus Verilog
$end
$timescale
	1ns
$end
$scope module counter_tb $end
$var wire 4 ! value [3:0] $end
$var reg 1 " clk $end
$var reg 1 # reset $end
$upscope $end
$enddefinitions $end
#0
$dumpvars
0#
0"
bx !
$end
#5
1"
#10
0"
#15
1"
#17
1#
#20
0"
#25
b0 !
1"
#28
0#
#30
0"
#35
b1 !
1"
#40
0"
#45
b10 !
1"
#50
0"
#55
b11 !
1"
#57
1#
#60
0"
#65
b0 !
1"
#68
0#
#70
0"
#75
b1 !
1"
#80
0"
#85
b10 !
1"
#90
0"
#95
b11 !
1"
#100
0"
#105
b100 !
1"
#110
0"
#115
b101 !
1"
#120
0"
#125
b110 !
1"
#130
0"
#135
b111 !
1"
#140
0"
#145
b1000 !
1"
#150
0"
#155
b1001 !
1"
#160
0"
#165
b1010 !
1"
#170
0"
#175
b1011 !
1"
#180
0"
#185
b1100 !
1"
#190
0"
#195
b1101 !
1"
#200
0"
#205
b1110 !
1"
#210
0"
#215
b1111 !
1"
#220
0"
#225
b0 !
1"
#230
0"
#235
b1 !
1"
#240
0"
#245
b10 !
1"
#250
0"
#255
b11 !
1"
#260
0"
#265
b100 !
1"
